maskcovid.py
maskcovid-0.0.3.dist-info/LICENSE
maskcovid-0.0.3.dist-info/METADATA
maskcovid-0.0.3.dist-info/WHEEL
maskcovid-0.0.3.dist-info/entry_points.txt
maskcovid-0.0.3.dist-info/top_level.txt
maskcovid-0.0.3.dist-info/RECORD
