Metadata-Version: 2.1
Name: maskcovid
Version: 0.0.3
Summary: maskcovid is a PyPI tool that predicts the number of people infected by day and up to one month from the date Japan began its liberal mask-wearing policy in the current Covid-19 epidemic.
Home-page: https://github.com/i-inose/maskcovid
Author: Izuru Inose
Author-email: i.inose0304@gmail.com
Project-URL: Bug Tracker, https://github.com/i-inose/maskcovid
Classifier: Programming Language :: Python :: 3
Classifier: License :: OSI Approved :: MIT License
Classifier: Operating System :: OS Independent
Requires-Python: >=3.7
License-File: LICENSE
